{
  "id": 10000083,
  "name": "琳妮特",
  "abbr": "琳妮特",
  "title": "丽影绮行",
  "star": 4,
  "elem": "anemo",
  "allegiance": "布法蒂公馆",
  "weapon": "sword",
  "birth": "2-2",
  "astro": "白尾猫座",
  "desc": "寡言少语，罕有表情的魔术助手，性情像猫一样难以猜测。",
  "cncv": "可可味",
  "jpcv": "篠原侑",
  "costume": false,
  "ver": 1,
  "baseAttr": {
    "hp": 12397,
    "atk": 231.51,
    "def": 711.87
  },
  "growAttr": {
    "key": "dmg",
    "value": 24
  },
  "talentId": {
    "10831": "a",
    "10832": "e",
    "10835": "q"
  },
  "talentCons": {
    "a": 0,
    "e": 5,
    "q": 3
  },
  "materials": {
    "gem": "自在松石",
    "boss": "奇械发条备件·歌裴莉娅",
    "specialty": "柔灯铃",
    "normal": "奇械机芯齿轮",
    "talent": "「秩序」的哲学",
    "weekly": "亘古树海之一瞬"
  },
  "talent": {
    "a": {
      "id": 8331,
      "name": "普通攻击·迅捷礼刺剑",
      "desc": [
        "<h3>普通攻击</h3>",
        "进行至多四段的连续剑击。",
        "<h3>重击</h3>",
        "消耗一定体力，瞬间向前方挥出两剑。",
        "<h3>下落攻击</h3>",
        "从空中下坠冲击地面，攻击下落路径上的敌人，并在落地时造成范围伤害。"
      ],
      "tables": [
        {
          "name": "一段伤害",
          "unit": "",
          "isSame": false,
          "values": [
            "43.08%",
            "46.59%",
            "50.09%",
            "55.1%",
            "58.61%",
            "62.62%",
            "68.13%",
            "73.64%",
            "79.15%",
            "85.16%",
            "91.17%",
            "97.18%",
            "103.2%",
            "109.21%",
            "115.22%"
          ]
        },
        {
          "name": "二段伤害",
          "unit": "",
          "isSame": false,
          "values": [
            "37.61%",
            "40.67%",
            "43.74%",
            "48.11%",
            "51.17%",
            "54.67%",
            "59.48%",
            "64.29%",
            "69.1%",
            "74.35%",
            "79.6%",
            "84.85%",
            "90.09%",
            "95.34%",
            "100.59%"
          ]
        },
        {
          "name": "三段伤害",
          "unit": "",
          "isSame": false,
          "values": [
            "27.86% + 21.59%",
            "30.13% + 23.35%",
            "32.4% + 25.11%",
            "35.64% + 27.62%",
            "37.91% + 29.38%",
            "40.5% + 31.38%",
            "44.06% + 34.15%",
            "47.63% + 36.91%",
            "51.19% + 39.67%",
            "55.08% + 42.68%",
            "58.97% + 45.7%",
            "62.86% + 48.71%",
            "66.74% + 51.72%",
            "70.63% + 54.74%",
            "74.52% + 57.75%"
          ]
        },
        {
          "name": "四段伤害",
          "unit": "",
          "isSame": false,
          "values": [
            "63.15%",
            "68.29%",
            "73.44%",
            "80.78%",
            "85.92%",
            "91.79%",
            "99.87%",
            "107.95%",
            "116.03%",
            "124.84%",
            "133.65%",
            "142.46%",
            "151.28%",
            "160.09%",
            "168.9%"
          ]
        },
        {
          "name": "重击伤害",
          "unit": "",
          "isSame": false,
          "values": [
            "44.2% + 61.4%",
            "47.8% + 66.4%",
            "51.4% + 71.4%",
            "56.54% + 78.54%",
            "60.14% + 83.54%",
            "64.25% + 89.25%",
            "69.9% + 97.1%",
            "75.56% + 104.96%",
            "81.21% + 112.81%",
            "87.38% + 121.38%",
            "93.55% + 129.95%",
            "99.72% + 138.52%",
            "105.88% + 147.08%",
            "112.05% + 155.65%",
            "118.22% + 164.22%"
          ]
        },
        {
          "name": "重击体力消耗",
          "unit": "",
          "isSame": true,
          "values": [
            "20点",
            "20点",
            "20点",
            "20点",
            "20点",
            "20点",
            "20点",
            "20点",
            "20点",
            "20点",
            "20点",
            "20点",
            "20点",
            "20点",
            "20点"
          ]
        },
        {
          "name": "下坠期间伤害",
          "unit": "",
          "isSame": false,
          "values": [
            "63.93%",
            "69.14%",
            "74.34%",
            "81.77%",
            "86.98%",
            "92.93%",
            "101.1%",
            "109.28%",
            "117.46%",
            "126.38%",
            "135.3%",
            "144.22%",
            "153.14%",
            "162.06%",
            "170.98%"
          ]
        },
        {
          "name": "低空/高空坠地冲击伤害",
          "unit": "",
          "isSame": false,
          "values": [
            "127.84% / 159.68%",
            "138.24% / 172.67%",
            "148.65% / 185.67%",
            "163.51% / 204.24%",
            "173.92% / 217.23%",
            "185.81% / 232.09%",
            "202.16% / 252.51%",
            "218.51% / 272.93%",
            "234.86% / 293.36%",
            "252.7% / 315.64%",
            "270.54% / 337.92%",
            "288.38% / 360.2%",
            "306.22% / 382.48%",
            "324.05% / 404.76%",
            "341.89% / 427.04%"
          ]
        }
      ]
    },
    "e": {
      "id": 8332,
      "name": "谜影障身法",
      "desc": [
        "挥舞斗篷，击出谜影突刺，造成风元素伤害。",
        "谜影突刺命中敌人时，将为琳妮特恢复生命值，回复量基于琳妮特的生命值上限，并在此后的4秒内，每秒将消耗一定的生命值。",
        "依据点按、长按，以不同的方式击出谜影突刺。",
        "<h3>点按</h3>",
        "迅速击出谜影突刺。",
        "<h3>长按</h3>",
        "琳妮特以「谜身影盗」的姿态疾走，并对附近的敌人施加「刺影征标」。期间可以控制疾走的方向，并能通过再次施放技能，提前结束疾走状态。",
        "疾走结束时，琳妮特将击出谜影突刺。若附近存在具有刺影征标的敌人，琳妮特将在击出谜影突刺前高速闪掠接近该敌人。",
        "同时至多有一名敌人具有琳妮特自身施加的刺影征标。与具有刺影征标的敌人距离过远时，将移除该刺影征标。",
        "<h3>始基力：荒性</h3>",
        "每隔一段时间，琳妮特击出谜影突刺时，将唤出流涌之刃，造成具有荒性的风元素伤害。",
        "<i>「现在就将视线转回台上，继续观赏表演吧。当我再次出现，就会是在你意想不到的地方了。」</i>"
      ],
      "tables": [
        {
          "name": "谜影突刺伤害",
          "unit": "",
          "isSame": false,
          "values": [
            "268%",
            "288.1%",
            "308.2%",
            "335%",
            "355.1%",
            "375.2%",
            "402%",
            "428.8%",
            "455.6%",
            "482.4%",
            "509.2%",
            "536%",
            "569.5%",
            "603%",
            "636.5%"
          ]
        },
        {
          "name": "流涌之刃伤害",
          "unit": "",
          "isSame": false,
          "values": [
            "31.2%",
            "33.54%",
            "35.88%",
            "39%",
            "41.34%",
            "43.68%",
            "46.8%",
            "49.92%",
            "53.04%",
            "56.16%",
            "59.28%",
            "62.4%",
            "66.3%",
            "70.2%",
            "74.1%"
          ]
        },
        {
          "name": "流涌之刃间隔",
          "unit": "",
          "isSame": true,
          "values": [
            "10秒",
            "10秒",
            "10秒",
            "10秒",
            "10秒",
            "10秒",
            "10秒",
            "10秒",
            "10秒",
            "10秒",
            "10秒",
            "10秒",
            "10秒",
            "10秒",
            "10秒"
          ]
        },
        {
          "name": "命中治疗量",
          "unit": "生命值上限",
          "isSame": false,
          "values": [
            "25%",
            "25%",
            "25%",
            "25%",
            "25%",
            "25%",
            "25%",
            "25%",
            "25%",
            "25%",
            "25%",
            "25%",
            "25%",
            "25%",
            "25%"
          ]
        },
        {
          "name": "生命值消耗",
          "unit": "",
          "isSame": true,
          "values": [
            "6%当前生命值 / 秒",
            "6%当前生命值 / 秒",
            "6%当前生命值 / 秒",
            "6%当前生命值 / 秒",
            "6%当前生命值 / 秒",
            "6%当前生命值 / 秒",
            "6%当前生命值 / 秒",
            "6%当前生命值 / 秒",
            "6%当前生命值 / 秒",
            "6%当前生命值 / 秒",
            "6%当前生命值 / 秒",
            "6%当前生命值 / 秒",
            "6%当前生命值 / 秒",
            "6%当前生命值 / 秒",
            "6%当前生命值 / 秒"
          ]
        },
        {
          "name": "长按最大持续时间",
          "unit": "",
          "isSame": true,
          "values": [
            "2.5秒",
            "2.5秒",
            "2.5秒",
            "2.5秒",
            "2.5秒",
            "2.5秒",
            "2.5秒",
            "2.5秒",
            "2.5秒",
            "2.5秒",
            "2.5秒",
            "2.5秒",
            "2.5秒",
            "2.5秒",
            "2.5秒"
          ]
        },
        {
          "name": "冷却时间",
          "unit": "",
          "isSame": true,
          "values": [
            "12秒",
            "12秒",
            "12秒",
            "12秒",
            "12秒",
            "12秒",
            "12秒",
            "12秒",
            "12秒",
            "12秒",
            "12秒",
            "12秒",
            "12秒",
            "12秒",
            "12秒"
          ]
        }
      ]
    },
    "q": {
      "id": 8339,
      "name": "魔术·运变惊奇",
      "desc": [
        "琳妮特高举斗篷造成风元素范围伤害，用惊人的手法变出巨大的惊奇猫猫盒！",
        "<h3>惊奇猫猫盒</h3>",
        "·能够持续嘲讽周围的敌人，吸引敌人攻击；",
        "·将周期性对附近的敌人造成风元素伤害；",
        "·惊奇猫猫盒接触了水元素/火元素/冰元素/雷元素，则会获得对应元素属性，周期性对附近的敌人追加发射彩练术弹，造成该元素的伤害。",
        "元素转化在技能持续期间仅会发生一次。",
        "<i>「就看向这个方向，看仔细。这是独属于我们的，奇迹时刻。」</i>"
      ],
      "tables": [
        {
          "name": "技能伤害",
          "unit": "",
          "isSame": false,
          "values": [
            "83.2%",
            "89.44%",
            "95.68%",
            "104%",
            "110.24%",
            "116.48%",
            "124.8%",
            "133.12%",
            "141.44%",
            "149.76%",
            "158.08%",
            "166.4%",
            "176.8%",
            "187.2%",
            "197.6%"
          ]
        },
        {
          "name": "惊奇猫猫盒伤害",
          "unit": "",
          "isSame": false,
          "values": [
            "51.2%",
            "55.04%",
            "58.88%",
            "64%",
            "67.84%",
            "71.68%",
            "76.8%",
            "81.92%",
            "87.04%",
            "92.16%",
            "97.28%",
            "102.4%",
            "108.8%",
            "115.2%",
            "121.6%"
          ]
        },
        {
          "name": "彩练术弹伤害",
          "unit": "",
          "isSame": false,
          "values": [
            "45.6%",
            "49.02%",
            "52.44%",
            "57%",
            "60.42%",
            "63.84%",
            "68.4%",
            "72.96%",
            "77.52%",
            "82.08%",
            "86.64%",
            "91.2%",
            "96.9%",
            "102.6%",
            "108.3%"
          ]
        },
        {
          "name": "惊奇猫猫盒持续时间",
          "unit": "",
          "isSame": true,
          "values": [
            "12秒",
            "12秒",
            "12秒",
            "12秒",
            "12秒",
            "12秒",
            "12秒",
            "12秒",
            "12秒",
            "12秒",
            "12秒",
            "12秒",
            "12秒",
            "12秒",
            "12秒"
          ]
        },
        {
          "name": "冷却时间",
          "unit": "",
          "isSame": true,
          "values": [
            "18秒",
            "18秒",
            "18秒",
            "18秒",
            "18秒",
            "18秒",
            "18秒",
            "18秒",
            "18秒",
            "18秒",
            "18秒",
            "18秒",
            "18秒",
            "18秒",
            "18秒"
          ]
        },
        {
          "name": "元素能量",
          "unit": "",
          "isSame": true,
          "values": [
            "70",
            "70",
            "70",
            "70",
            "70",
            "70",
            "70",
            "70",
            "70",
            "70",
            "70",
            "70",
            "70",
            "70",
            "70"
          ]
        }
      ]
    }
  },
  "talentData": {
    "a": {
      "一段伤害": [
        43.08,
        46.59,
        50.09,
        55.1,
        58.61,
        62.62,
        68.13,
        73.64,
        79.15,
        85.16,
        91.17,
        97.18,
        103.2,
        109.21,
        115.22
      ],
      "二段伤害": [
        37.61,
        40.67,
        43.74,
        48.11,
        51.17,
        54.67,
        59.48,
        64.29,
        69.1,
        74.35,
        79.6,
        84.85,
        90.09,
        95.34,
        100.59
      ],
      "三段伤害": [
        49.45,
        53.480000000000004,
        57.51,
        63.260000000000005,
        67.28999999999999,
        71.88,
        78.21000000000001,
        84.53999999999999,
        90.86,
        97.75999999999999,
        104.67,
        111.57,
        118.46,
        125.37,
        132.26999999999998
      ],
      "三段伤害2": [
        [
          27.86,
          21.59
        ],
        [
          30.13,
          23.35
        ],
        [
          32.4,
          25.11
        ],
        [
          35.64,
          27.62
        ],
        [
          37.91,
          29.38
        ],
        [
          40.5,
          31.38
        ],
        [
          44.06,
          34.15
        ],
        [
          47.63,
          36.91
        ],
        [
          51.19,
          39.67
        ],
        [
          55.08,
          42.68
        ],
        [
          58.97,
          45.7
        ],
        [
          62.86,
          48.71
        ],
        [
          66.74,
          51.72
        ],
        [
          70.63,
          54.74
        ],
        [
          74.52,
          57.75
        ]
      ],
      "四段伤害": [
        63.15,
        68.29,
        73.44,
        80.78,
        85.92,
        91.79,
        99.87,
        107.95,
        116.03,
        124.84,
        133.65,
        142.46,
        151.28,
        160.09,
        168.9
      ],
      "重击伤害": [
        105.6,
        114.2,
        122.80000000000001,
        135.08,
        143.68,
        153.5,
        167,
        180.51999999999998,
        194.01999999999998,
        208.76,
        223.5,
        238.24,
        252.96,
        267.7,
        282.44
      ],
      "重击伤害2": [
        [
          44.2,
          61.4
        ],
        [
          47.8,
          66.4
        ],
        [
          51.4,
          71.4
        ],
        [
          56.54,
          78.54
        ],
        [
          60.14,
          83.54
        ],
        [
          64.25,
          89.25
        ],
        [
          69.9,
          97.1
        ],
        [
          75.56,
          104.96
        ],
        [
          81.21,
          112.81
        ],
        [
          87.38,
          121.38
        ],
        [
          93.55,
          129.95
        ],
        [
          99.72,
          138.52
        ],
        [
          105.88,
          147.08
        ],
        [
          112.05,
          155.65
        ],
        [
          118.22,
          164.22
        ]
      ],
      "下坠期间伤害": [
        63.93,
        69.14,
        74.34,
        81.77,
        86.98,
        92.93,
        101.1,
        109.28,
        117.46,
        126.38,
        135.3,
        144.22,
        153.14,
        162.06,
        170.98
      ],
      "低空/高空坠地冲击伤害": [
        [
          127.84,
          159.68
        ],
        [
          138.24,
          172.67
        ],
        [
          148.65,
          185.67
        ],
        [
          163.51,
          204.24
        ],
        [
          173.92,
          217.23
        ],
        [
          185.81,
          232.09
        ],
        [
          202.16,
          252.51
        ],
        [
          218.51,
          272.93
        ],
        [
          234.86,
          293.36
        ],
        [
          252.7,
          315.64
        ],
        [
          270.54,
          337.92
        ],
        [
          288.38,
          360.2
        ],
        [
          306.22,
          382.48
        ],
        [
          324.05,
          404.76
        ],
        [
          341.89,
          427.04
        ]
      ],
      "低空/高空坠地冲击伤害2": [
        [
          127.84,
          159.68
        ],
        [
          138.24,
          172.67
        ],
        [
          148.65,
          185.67
        ],
        [
          163.51,
          204.24
        ],
        [
          173.92,
          217.23
        ],
        [
          185.81,
          232.09
        ],
        [
          202.16,
          252.51
        ],
        [
          218.51,
          272.93
        ],
        [
          234.86,
          293.36
        ],
        [
          252.7,
          315.64
        ],
        [
          270.54,
          337.92
        ],
        [
          288.38,
          360.2
        ],
        [
          306.22,
          382.48
        ],
        [
          324.05,
          404.76
        ],
        [
          341.89,
          427.04
        ]
      ]
    },
    "e": {
      "谜影突刺伤害": [
        268,
        288.1,
        308.2,
        335,
        355.1,
        375.2,
        402,
        428.8,
        455.6,
        482.4,
        509.2,
        536,
        569.5,
        603,
        636.5
      ],
      "流涌之刃伤害": [
        31.2,
        33.54,
        35.88,
        39,
        41.34,
        43.68,
        46.8,
        49.92,
        53.04,
        56.16,
        59.28,
        62.4,
        66.3,
        70.2,
        74.1
      ],
      "命中治疗量": [
        25,
        25,
        25,
        25,
        25,
        25,
        25,
        25,
        25,
        25,
        25,
        25,
        25,
        25,
        25
      ]
    },
    "q": {
      "技能伤害": [
        83.2,
        89.44,
        95.68,
        104,
        110.24,
        116.48,
        124.8,
        133.12,
        141.44,
        149.76,
        158.08,
        166.4,
        176.8,
        187.2,
        197.6
      ],
      "惊奇猫猫盒伤害": [
        51.2,
        55.04,
        58.88,
        64,
        67.84,
        71.68,
        76.8,
        81.92,
        87.04,
        92.16,
        97.28,
        102.4,
        108.8,
        115.2,
        121.6
      ],
      "彩练术弹伤害": [
        45.6,
        49.02,
        52.44,
        57,
        60.42,
        63.84,
        68.4,
        72.96,
        77.52,
        82.08,
        86.64,
        91.2,
        96.9,
        102.6,
        108.3
      ]
    }
  },
  "cons": {
    "1": {
      "name": "如影流露的冷刃",
      "desc": [
        "谜影障身法的谜影突刺命中带有刺影征标的敌人时，将在敌人的位置生成风涡，牵引附近的敌人。"
      ]
    },
    "2": {
      "name": "层见叠出的谜象",
      "desc": [
        "魔术·运变惊奇召唤的惊奇猫猫盒发射彩练术弹时，将额外发射一枚彩练术弹。"
      ]
    },
    "3": {
      "name": "倒错知能的视度",
      "desc": [
        "魔术·运变惊奇的技能等级提高3级。",
        "至多提升至15级。"
      ]
    },
    "4": {
      "name": "灵犀默应的配合",
      "desc": [
        "谜影障身法的可使用次数增加1次。"
      ]
    },
    "5": {
      "name": "暗昧遮目的障法",
      "desc": [
        "谜影障身法的技能等级提高3级。",
        "至多提升至15级。"
      ]
    },
    "6": {
      "name": "示辨真意的眼",
      "desc": [
        "琳妮特施放谜影障身法的谜影突刺时，将获得风元素附魔，风元素伤害加成提升20%，持续6秒。"
      ]
    }
  },
  "passive": [
    {
      "name": "点位记忆法",
      "desc": [
        "在小地图上显示周围复苏水团的位置，并使接触复苏水团时恢复的水中耐力与生命值提升25%。"
      ]
    },
    {
      "name": "巧施协同",
      "desc": [
        "施放魔术·运变惊奇后的10秒内，队伍中分别存在1/2/3/4种元素类型的角色时，队伍中所有角色的攻击力分别提升8%/12%/16%/20%。"
      ]
    },
    {
      "name": "道具完备",
      "desc": [
        "魔术·运变惊奇召唤的惊奇猫猫盒发生了元素转化后，琳妮特元素爆发造成的伤害提升15%，效果持续至该惊奇猫猫盒持续时间结束。"
      ]
    }
  ],
  "attr": {
    "keys": [
      "hpBase",
      "atkBase",
      "defBase",
      "dmg"
    ],
    "details": {
      "1": [
        1039,
        19.41,
        59.69,
        0
      ],
      "20": [
        2670,
        49.87,
        153.33,
        0
      ],
      "40": [
        5163,
        96.41,
        296.46,
        0
      ],
      "50": [
        6573,
        122.75,
        377.44,
        6
      ],
      "60": [
        8168,
        152.52,
        468.99,
        12
      ],
      "70": [
        9577,
        178.84,
        549.91,
        12
      ],
      "80": [
        10987,
        205.18,
        630.89,
        18
      ],
      "90": [
        12397,
        231.51,
        711.87,
        24
      ],
      "20+": [
        3447,
        64.37,
        197.92,
        0
      ],
      "40+": [
        5715,
        106.72,
        328.14,
        6
      ],
      "50+": [
        7309,
        136.49,
        419.68,
        12
      ],
      "60+": [
        8719,
        162.83,
        500.67,
        12
      ],
      "70+": [
        10129,
        189.14,
        581.59,
        18
      ],
      "80+": [
        11539,
        215.48,
        662.57,
        24
      ]
    }
  }
}