{
  "id": 10000020,
  "name": "雷泽",
  "abbr": "雷泽",
  "title": "狼少年",
  "star": 4,
  "elem": "electro",
  "allegiance": "奔狼领",
  "weapon": "claymore",
  "birth": "9-9",
  "astro": "小狼座",
  "desc": "住在蒙德地区奔狼领，远离城市与人群，和狼一同生活的少年。直觉锐利，身姿迅捷。",
  "cncv": "周帅",
  "jpcv": "内山昂辉",
  "costume": false,
  "ver": 1,
  "baseAttr": {
    "hp": 11962,
    "atk": 233.64,
    "def": 750.77
  },
  "growAttr": {
    "key": "phy",
    "value": 30
  },
  "talentId": {
    "10201": "a",
    "10202": "e",
    "10203": "q"
  },
  "talentCons": {
    "e": 5,
    "q": 3
  },
  "materials": {
    "gem": "最胜紫晶",
    "boss": "雷光棱镜",
    "specialty": "钩钩果",
    "normal": "不祥的面具",
    "talent": "「抗争」的哲学",
    "weekly": "东风之爪"
  }
}